deep_forge_ai/__init__.py
deep_forge_ai/ai_interactor.py
deep_forge_ai/api_client.py
deep_forge_ai/data_models.py
deep_forge_ai/db_connector.py
deep_forge_ai/db_manager.py
deep_forge_ai/is_working.py
deep_forge_ai/prompt_builder.py
deep_forge_ai/sql_validator.py
deep_forge_ai-0.1.5.dist-info/licenses/LICENSE
deep_forge_ai-0.1.5.dist-info/METADATA
deep_forge_ai-0.1.5.dist-info/WHEEL
deep_forge_ai-0.1.5.dist-info/top_level.txt
deep_forge_ai-0.1.5.dist-info/RECORD
