Metadata-Version: 2.4
Name: deep-forge-ai
Version: 0.1.5
Summary: DeepForge is a Python library designed to empower SMEs with advanced AI agents for sales and customer service automation. It uniquely ensures absolute data sovereignty by operating directly on your server, leveraging your existing databases for intelligent, personalized interactions.
Author-email: Qodirov Muhammadkarim <muhammadkarimqodirov111@gmail.com>
Project-URL: Homepage, https://github.com/deep-forge/deep-forge-library
Project-URL: Bug Tracker, https://github.com/deep-forge/deep-forge-library/issues
Classifier: Programming Language :: Python :: 3
Classifier: Programming Language :: Python :: 3.8
Classifier: Programming Language :: Python :: 3.9
Classifier: Programming Language :: Python :: 3.10
Classifier: Programming Language :: Python :: 3.11
Classifier: Programming Language :: Python :: 3.12
Classifier: License :: OSI Approved :: MIT License
Classifier: Operating System :: OS Independent
Classifier: Development Status :: 3 - Alpha
Classifier: Intended Audience :: Developers
Classifier: Topic :: Scientific/Engineering :: Artificial Intelligence
Classifier: Topic :: Software Development :: Libraries :: Python Modules
Classifier: Topic :: Office/Business
Classifier: Topic :: System :: Networking
Requires-Python: >=3.8
License-File: LICENSE
Requires-Dist: requests>=2.0.0
Requires-Dist: pydantic>=2.0
Requires-Dist: google-generativeai>=0.4.1
Requires-Dist: sqlalchemy>=1.4
Requires-Dist: sqlparse>=0.4.0
Dynamic: license-file
